dora_lead_time/__init__.py
dora_lead_time/atlassian_requests.py
dora_lead_time/database_processor.py
dora_lead_time/date_utility.py
dora_lead_time/github_requests.py
dora_lead_time/lead_time_report.py
dora_lead_time/main.py
dora_lead_time/models.py
dora_lead_time/outlier_reports/A_projects_without_releases.sql
dora_lead_time/outlier_reports/B_releases_with_open_stories.sql
dora_lead_time/outlier_reports/C_stories_in_multiple_releases.sql
dora_lead_time/outlier_reports/D_releases_with_open_pull_requests.sql
dora_lead_time/outlier_reports/E_counts_of_stories_without_pull_requests.sql
dora_lead_time/outlier_reports/E_stories_without_pull_requests.sql
dora_lead_time/outlier_reports/F_pull_requests_with_old_commits.sql
dora_lead_time/outlier_reports/G_zero_or_negative_lead_times.sql
dora_lead_time/outlier_reports.py
dora_lead_time/schema/schema.sql
dora_lead_time_metric-1.2.2.dist-info/METADATA
dora_lead_time_metric-1.2.2.dist-info/WHEEL
dora_lead_time_metric-1.2.2.dist-info/entry_points.txt
dora_lead_time_metric-1.2.2.dist-info/RECORD
