Metadata-Version: 2.4
Name: dora-lead-time-metric
Version: 1.2.2
Summary: A tool to calculate the DORA Lead Time metric
Author: Sualeh Fatehi
Author-email: sualeh@hotmail.com
Requires-Python: >=3.13,<4.0
Classifier: Programming Language :: Python :: 3
Classifier: Programming Language :: Python :: 3.13
Classifier: Programming Language :: Python :: 3.14
Provides-Extra: dev
Requires-Dist: black (>=24.2.0,<25.0.0) ; extra == "dev"
Requires-Dist: matplotlib (>=3.10.0,<4.0.0)
Requires-Dist: numpy (>=2.2.3,<3.0.0)
Requires-Dist: pandas (>=2.2.3,<3.0.0)
Requires-Dist: pycobertura (>=4.0.0,<5.0.0) ; extra == "dev"
Requires-Dist: pylint (>=3.0.2,<4.0.0) ; extra == "dev"
Requires-Dist: pytest (>=8.0.0,<9.0.0) ; extra == "dev"
Requires-Dist: pytest-cov (>=5.0.0,<6.0.0) ; extra == "dev"
Requires-Dist: python-dotenv (>=1.1.0,<2.0.0)
Requires-Dist: requests (>=2.32.3,<3.0.0)
